dbManager/__init__.py
dbManager/main.py
dbManager/tempCodeRunnerFile.py
dbManager/jwlibrary/__init__.py
dbManager/jwlibrary/main.py
dbManager/jwlibrary/notes.py
dbManager/jwlibrary/utils.py
allindb-1.0.3.dist-info/METADATA
allindb-1.0.3.dist-info/WHEEL
allindb-1.0.3.dist-info/entry_points.txt
allindb-1.0.3.dist-info/top_level.txt
allindb-1.0.3.dist-info/RECORD
