Metadata-Version: 2.1
Name: allindb
Version: 1.0.3
Summary: A powerful database and jwlibrary manager
Home-page: https://github.com/acalasanzs/WA4TXT_LAB
Author: Albert Calasanz Sallen
Author-email: acalasanzs@gmail.com
Project-URL: Bug Tracker, https://github.com/acalasanzs/WA4TXT_LAB/issues
Classifier: Programming Language :: Python :: 3
Classifier: License :: OSI Approved :: MIT License
Classifier: Operating System :: OS Independent
Requires-Python: >=3.6
